{
  "pubbs_ind": [
    {
      "id": "1",
      "type": "Articolo in rivista",
      "parsed": {
        "titolo": "Stefano Langton sul battesimo. Edizione delle Quaestiones",
        "ISSN": [
          "0391-2566"
        ],
        "journal": "MEDIOEVO: RIVISTA DI STORIA DELLA FILOSOFIA MEDIEVALE",
        "csp": "vol. 40, p. 197-264, ISSN: 0391-2566",
        "anno": "2016",
        "autori": "SACCENTI R"
      },
      "rawcontent": [
        "Articolo in rivista",
        "SACCENTI R (2016). Stefano Langton sul battesimo. Edizione delle",
        "Quaestiones. MEDIOEVO: RIVISTA DI STORIA DELLA FILOSOFIA",
        "MEDIEVALE, vol. 40, p. 197-264, ISSN: 0391-2566"
      ],
      "anno": "2016"
    },
    {
      "id": "2",
      "type": "Contributo in volume (Capitolo o Saggio)",
      "parsed": {
        "precsp": "211-230",
        "titolo": "Le piaghe della Chiesa italiana",
        "csp": "ROMA: Istituto della Enciclopedia Italiana fondata da Giovanni Treccani S.p.A",
        "opera": "(a cura di): MELLONI A, Misericordiae vultus. Il Giubileo di Papa Francesco. p",
        "anno": "2016",
        "autori": "SACCENTI R"
      },
      "rawcontent": [
        "Contributo in volume (Capitolo o Saggio)",
        "SACCENTI R (2016). Le piaghe della Chiesa italiana. In: (a cura di):",
        "MELLONI A, Misericordiae vultus. Il Giubileo di Papa Francesco. p.",
        "211-230, ROMA: Istituto della Enciclopedia Italiana fondata da Giovanni",
        "Treccani S.p.A"
      ],
      "anno": "2016"
    },
    {
      "id": "3",
      "type": "Contributo in volume (Capitolo o Saggio)",
      "parsed": {
        "precsp": "32-44",
        "titolo": "The decree Exivi de Paradiso and its implications for mendicant poverty",
        "ISBN": [
          "978-1-4724-3732-7"
        ],
        "csp": "LONDON-NEW YORK:Routledge Taylor & Francis Group, ISBN: 978-1-4724-3732-7",
        "opera": "(a cura di): MEWS CJ; WELCH A, Poverty and Devotion in Mendicant Cultures. 1200-1450. p",
        "anno": "2016",
        "autori": "SACCENTI R"
      },
      "rawcontent": [
        "Contributo in volume (Capitolo o Saggio)",
        "SACCENTI R (2016). The decree Exivi de Paradiso and its implications for",
        "mendicant poverty. In: (a cura di): MEWS CJ; WELCH A, Poverty and",
        "Devotion in Mendicant Cultures. 1200-1450. p. 32-44, LONDON-NEW",
        "YORK:Routledge Taylor & Francis Group, ISBN: 978-1-4724-3732-7"
      ],
      "anno": "2016"
    },
    {
      "id": "4",
      "type": "Contributo in Atti di convegno",
      "parsed": {
        "precsp": "123-171",
        "titolo": "La distinctio prima di Graziano e il dibattito sulla legge di natura nel XV secolo",
        "ISBN": [
          "978-88-548-8169-3"
        ],
        "csp": "Arriccia (RM):Aracne editrice int.le S.r.l., ISBN: 978-88-548-8169-3, Modena-Bologna, 28-29 novembre 2013",
        "opera": "(a cura di): Sulas C; Saccenti R, Legge e Natura. I dibattiti teologici e giuridici fra XV e XVII secolo. Atti del Convegno. Modena-Bologna, 28-29 novembre 2013. p",
        "anno": "2016",
        "autori": "SACCENTI R"
      },
      "rawcontent": [
        "Contributo in Atti di convegno",
        "SACCENTI R (2016). La distinctio prima di Graziano e il dibattito sulla",
        "legge di natura nel XV secolo. In: (a cura di): Sulas C; Saccenti R, Legge e",
        "Natura. I dibattiti teologici e giuridici fra XV e XVII secolo. Atti del",
        "Convegno. Modena-Bologna, 28-29 novembre 2013. p. 123-171, Arriccia",
        "(RM):Aracne editrice int.le S.r.l., ISBN: 978-88-548-8169-3,",
        "Modena-Bologna, 28-29 novembre 2013"
      ],
      "anno": "2016"
    },
    {
      "id": "5",
      "type": "Monografia o trattato scientifico",
      "parsed": {
        "precsp": "1-170",
        "titolo": "Debetaing Medieval Natural Law: A Survey. p",
        "ISBN": [
          "978-0-268-10040-7"
        ],
        "csp": "NOTRE DAME, IND.:University of Notre Dame Press, ISBN: 978-0-268-10040-7",
        "anno": "2016",
        "autori": "SACCENTI R"
      },
      "rawcontent": [
        "Monografia o trattato scientifico",
        "SACCENTI R (2016). Debetaing Medieval Natural Law: A Survey. p. 1-170,",
        "NOTRE DAME, IND.:University of Notre Dame Press, ISBN:",
        "978-0-268-10040-7"
      ],
      "anno": "2016"
    },
    {
      "id": "6",
      "type": "Contributo in volume (Capitolo o Saggio)",
      "parsed": {
        "precsp": "81-97",
        "titolo": "The Bible of Marco Polo (13th-18th centuries)",
        "ISBN": [
          "978-90-8209-094-9"
        ],
        "csp": "LEUVEN:Ferdinand Verbiest Institute, ISBN: 978-90-8209-094-9",
        "opera": "(a cura di): Ferdinand Verbiest Institute, History of the Catholic Church in China: From its Beginning to the Scheut Fathers and 20th Century. Unveiling some less known Sources, Sounds and Pictures. p",
        "anno": "2015",
        "autori": "SACCENTI R, FORESTA P"
      },
      "rawcontent": [
        "Contributo in volume (Capitolo o Saggio)",
        "SACCENTI R, FORESTA P (2015). The Bible of Marco Polo (13th-18th",
        "centuries). In: (a cura di): Ferdinand Verbiest Institute, History of the",
        "Catholic Church in China: From its Beginning to the Scheut Fathers and",
        "20th Century. Unveiling some less known Sources, Sounds and Pictures. p.",
        "81-97, LEUVEN:Ferdinand Verbiest Institute, ISBN: 978-90-8209-094-9"
      ],
      "anno": "2015"
    },
    {
      "id": "7",
      "type": "Voce (in dizionario o enciclopedia)",
      "parsed": {
        "titolo": "Pini Giandomenico",
        "opera": "Dizionario Biografico degli italiani. vol. 83, p. 748-749, ROMA: Istituto della Enciclopedia Italiana fondata da Giovanni Treccani S.p.A, ISBN: 978-88-12-00032-6",
        "anno": "2015",
        "autori": "SACCENTI R"
      },
      "rawcontent": [
        "Voce (in dizionario o enciclopedia)",
        "SACCENTI R (2015). Pini Giandomenico. In: Dizionario Biografico degli",
        "italiani. vol. 83, p. 748-749, ROMA: Istituto della Enciclopedia Italiana",
        "fondata da Giovanni Treccani S.p.A, ISBN: 978-88-12-00032-6"
      ],
      "anno": "2015"
    },
    {
      "id": "8",
      "type": "Articolo in rivista",
      "parsed": {
        "titolo": "Faith and connexio virtutum in the Treatise of the Theological Virtues in the First Theological Summas (1220s-1240s)",
        "ISSN": [
          "1612-3964"
        ],
        "journal": "ARCHA VERBI",
        "csp": "vol. 12, p. 221-235, ISSN: 1612-3964",
        "anno": "2014",
        "autori": "SACCENTI R"
      },
      "rawcontent": [
        "Articolo in rivista",
        "SACCENTI R (2014). Faith and connexio virtutum in the Treatise of the",
        "Theological Virtues in the First Theological Summas (1220s-1240s).",
        "ARCHA VERBI, vol. 12, p. 221-235, ISSN: 1612-3964"
      ],
      "anno": "2014"
    },
    {
      "id": "9",
      "type": "Contributo in volume (Capitolo o Saggio)",
      "parsed": {
        "precsp": "995-1004",
        "titolo": "Cognitio veritatis. La M\u00e9taphysique et l'Ethique d'Aristote comme source de l'anonyme \"Compendium philosophie\" (milieu du XIIIe si\u00e8cle)",
        "ISBN": [
          "978-88-8450-554-5"
        ],
        "csp": "SISMEL-EDIZIONI DEL GLLUZZO, ISBN: 978-88-8450-554-5",
        "opera": "(a cura di): D'Angelo E e Ziolkowski J, Auctor et auctoritas in Latinis Medii Aevi Litteris. Proceedings of the Sixth Congress of the International Medieval Committee. p",
        "anno": "2014",
        "autori": "SACCENTI R"
      },
      "rawcontent": [
        "Contributo in volume (Capitolo o Saggio)",
        "SACCENTI R (2014). Cognitio veritatis. La M\u00e9taphysique et l'Ethique",
        "d'Aristote comme source de l'anonyme \"Compendium philosophie\" (milieu",
        "du XIIIe si\u00e8cle). In: (a cura di): D'Angelo E e Ziolkowski J, Auctor et",
        "auctoritas in Latinis Medii Aevi Litteris. Proceedings of the Sixth Congress",
        "of the International Medieval Committee. p. 995-1004, SISMEL-EDIZIONI",
        "DEL GLLUZZO, ISBN: 978-88-8450-554-5"
      ],
      "anno": "2014"
    },
    {
      "id": "10",
      "type": "Articolo in rivista",
      "parsed": {
        "titolo": "THE MATERIA SUPER LIBROS SENTENTIARUM ATTRIBUTED TO PETER COMESTOR: STUDY OF THE TEXT AND CRITICAL EDITION",
        "ISSN": [
          "0068-4023"
        ],
        "journal": "BULLETIN DE PHILOSOPHIE MEDIEVALE",
        "csp": "vol. 54, p. 155-215, ISSN: 0068-4023",
        "anno": "2013",
        "autori": "SACCENTI R"
      },
      "rawcontent": [
        "Articolo in rivista",
        "SACCENTI R (2013). THE MATERIA SUPER LIBROS SENTENTIARUM",
        "ATTRIBUTED TO PETER COMESTOR: STUDY OF THE TEXT AND",
        "CRITICAL EDITION. BULLETIN DE PHILOSOPHIE MEDIEVALE, vol. 54,",
        "p. 155-215, ISSN: 0068-4023"
      ],
      "anno": "2013"
    },
    {
      "id": "11",
      "type": "Contributo in volume (Capitolo o Saggio)",
      "parsed": {
        "precsp": "597-620",
        "titolo": "COSTANTINO NEL DIRITTO CANONICO CLASSICO. ELEMENTI COSTANTINIANI NELLA CANONISTICA FRA XI E XIV SECOLO",
        "ISBN": [
          "978-88-12-00171-2"
        ],
        "csp": "ROMA:Istituto della Enciclopedia Italiana Treccani, ISBN: 978-88-12-00171-2",
        "opera": "(a cura di): MELLONI A.,RONCHEY S., TANNER N., BROWN P., PRINZIVALLI E., COSTANTINO I. ENCICLOPEDIA COSTANTINIANA SULLA FIGURA E L'IMMAGINE DELL'IMPERATORE DEL COSIDDETTO EDITTO DI MILANO, 313-2013. vol. 2, p",
        "anno": "2013",
        "autori": "SACCENTI R"
      },
      "rawcontent": [
        "Contributo in volume (Capitolo o Saggio)",
        "SACCENTI R (2013). COSTANTINO NEL DIRITTO CANONICO",
        "CLASSICO. ELEMENTI COSTANTINIANI NELLA CANONISTICA FRA XI",
        "E XIV SECOLO. In: (a cura di): MELLONI A.,RONCHEY S., TANNER N.,",
        "BROWN P., PRINZIVALLI E., COSTANTINO I. ENCICLOPEDIA",
        "COSTANTINIANA SULLA FIGURA E L'IMMAGINE DELL'IMPERATORE",
        "DEL COSIDDETTO EDITTO DI MILANO, 313-2013. vol. 2, p. 597-620,",
        "ROMA:Istituto della Enciclopedia Italiana Treccani, ISBN:",
        "978-88-12-00171-2"
      ],
      "anno": "2013"
    },
    {
      "id": "12",
      "type": "Contributo in volume (Capitolo o Saggio)",
      "parsed": {
        "precsp": "359-469",
        "titolo": "Concilium Viennense 1311-1312",
        "ISBN": [
          "978-2-503-52527-3"
        ],
        "ISSN": [
          "0589-7963"
        ],
        "csp": "TURNHOUT:Brepols, ISBN: 978-2-503-52527-3, ISSN: 0589-7963",
        "opera": "(a cura di): ALBERIGO G., MELLONI A., Conciliorum Oecumenicorum Generaliumque Decreta II/!. CORPUS CHRISTIANORUM. CONTINUATIO MEDIAEVALIS, vol. II/1, p",
        "anno": "2013",
        "autori": "SACCENTI R"
      },
      "rawcontent": [
        "Contributo in volume (Capitolo o Saggio)",
        "SACCENTI R (2013). Concilium Viennense 1311-1312. In: (a cura di):",
        "ALBERIGO G., MELLONI A., Conciliorum Oecumenicorum Generaliumque",
        "Decreta II/!. CORPUS CHRISTIANORUM. CONTINUATIO MEDIAEVALIS,",
        "vol. II/1, p. 359-469, TURNHOUT:Brepols, ISBN: 978-2-503-52527-3,",
        "ISSN: 0589-7963"
      ],
      "anno": "2013"
    },
    {
      "id": "13",
      "type": "Contributo in volume (Capitolo o Saggio)",
      "parsed": {
        "precsp": "275-293",
        "titolo": "Questions et Sentences: l'enseignement entre la fin du XIIe et le d\u00e9but du XIIIe si\u00e8cle",
        "ISBN": [
          "978-2-503-55154-8"
        ],
        "ISSN": [
          "2032-1252"
        ],
        "csp": "TURNHOUT:Brepols, ISBN: 978-2-503-55154-8, ISSN: 2032-1252",
        "opera": "(a cura di): VERGER J., WEIJERS O., Les d\u00e9buts de l'enseignement universitaire \u00e0 Paris (1200-1245 environ). STUDIA ARTISTARUM, vol. 38, p",
        "anno": "2013",
        "autori": "SACCENTI R"
      },
      "rawcontent": [
        "Contributo in volume (Capitolo o Saggio)",
        "SACCENTI R (2013). Questions et Sentences: l'enseignement entre la fin",
        "du XIIe et le d\u00e9but du XIIIe si\u00e8cle. In: (a cura di): VERGER J., WEIJERS",
        "O., Les d\u00e9buts de l'enseignement universitaire \u00e0 Paris (1200-1245 environ).",
        "STUDIA ARTISTARUM, vol. 38, p. 275-293, TURNHOUT:Brepols, ISBN:",
        "978-2-503-55154-8, ISSN: 2032-1252"
      ],
      "anno": "2013"
    },
    {
      "id": "14",
      "type": "Contributo in volume (Capitolo o Saggio)",
      "parsed": {
        "precsp": "247-275",
        "titolo": "LE FONTI DEL DE SERVORUM DEI E IL LORO USO NEL TRATTATO LAMBERTINIANO",
        "ISBN": [
          "978-88-6372-501-8"
        ],
        "csp": "ROMA:Edizioni di Storia e Letteratura, ISBN: 978-88-6372-501-8",
        "opera": "(a cura di): FATTORI MARIA TERESA, STORIA, MEDICINA E DIRITTO NEI TRATTATI DI PROSPERO LAMBERTINI BENEDETTO XIV. p",
        "anno": "2013",
        "autori": "SACCENTI R"
      },
      "rawcontent": [
        "Contributo in volume (Capitolo o Saggio)",
        "SACCENTI R (2013). LE FONTI DEL DE SERVORUM DEI E IL LORO",
        "USO NEL TRATTATO LAMBERTINIANO. In: (a cura di): FATTORI MARIA",
        "TERESA, STORIA, MEDICINA E DIRITTO NEI TRATTATI DI PROSPERO",
        "LAMBERTINI BENEDETTO XIV. p. 247-275, ROMA:Edizioni di Storia e",
        "Letteratura, ISBN: 978-88-6372-501-8"
      ],
      "anno": "2013"
    },
    {
      "id": "15",
      "type": "Voce (in dizionario o enciclopedia)",
      "parsed": {
        "titolo": "Niccol\u00f2 De' Mirabili",
        "opera": "Dizionario Biografico degli Italiani. vol. 78",
        "anno": "2013",
        "autori": "SACCENTI R"
      },
      "rawcontent": [
        "Voce (in dizionario o enciclopedia)",
        "SACCENTI R (2013). Niccol\u00f2 De' Mirabili. In: Dizionario Biografico degli",
        "Italiani. vol. 78"
      ],
      "anno": "2013"
    },
    {
      "id": "16",
      "type": "Voce (in dizionario o enciclopedia)",
      "parsed": {
        "titolo": "Romano Orsini",
        "opera": "Dizionario Biografico degli Italiani. vol. 79",
        "anno": "2013",
        "autori": "SACCENTI R"
      },
      "rawcontent": [
        "Voce (in dizionario o enciclopedia)",
        "SACCENTI R (2013). Romano Orsini. In: Dizionario Biografico degli Italiani.",
        "vol. 79"
      ],
      "anno": "2013"
    },
    {
      "id": "17",
      "type": "Monografia o trattato scientifico",
      "parsed": {
        "precsp": "1-248",
        "titolo": "CONSERVARE LA RETTA VOLONTA'. L'ATTO MORALE NELLE DOTTRINE DI FILIPPO IL CANCELLIERE E UGO SI SAINT-CHER (1225-1235). vol. 1, p",
        "ISBN": [
          "978-88-15-24453-6"
        ],
        "csp": "BOLOGNA:Il Mulino, ISBN: 978-88-15-24453-6",
        "anno": "2013",
        "autori": "SACCENTI R"
      },
      "rawcontent": [
        "Monografia o trattato scientifico",
        "SACCENTI R (2013). CONSERVARE LA RETTA VOLONTA'. L'ATTO",
        "MORALE NELLE DOTTRINE DI FILIPPO IL CANCELLIERE E UGO SI",
        "SAINT-CHER (1225-1235). vol. 1, p. 1-248, BOLOGNA:Il Mulino, ISBN:",
        "978-88-15-24453-6"
      ],
      "anno": "2013"
    },
    {
      "id": "18",
      "type": "Articolo in rivista",
      "parsed": {
        "titolo": "EUROPA E CINA NEL MEDIOEVO: LA BIBBIA DI MARCO POLO",
        "ISSN": [
          "0032-6925"
        ],
        "journal": "PRATO STORIA E ARTE",
        "csp": "vol. 112, p. 117-125, ISSN: 0032-6925",
        "anno": "2012",
        "autori": "SACCENTI R"
      },
      "rawcontent": [
        "Articolo in rivista",
        "SACCENTI R (2012). EUROPA E CINA NEL MEDIOEVO: LA BIBBIA DI",
        "MARCO POLO. PRATO STORIA E ARTE, vol. 112, p. 117-125, ISSN:",
        "0032-6925"
      ],
      "anno": "2012"
    },
    {
      "id": "19",
      "type": "Contributo in volume (Capitolo o Saggio)",
      "parsed": {
        "precsp": "219-226",
        "titolo": "La d\u00e9finition de vertu chez les th\u00e9ologiens de la premi\u00e8re moiti\u00e9 du XIIIe si\u00e8cle",
        "ISBN": [
          "9788864850498"
        ],
        "csp": "PALERMO:Officina Studi Medievali, ISBN: 9788864850498",
        "opera": "(a cura di): Musco A., Compagno C., D'Agostino S., Musotto G. , Universalit\u00e0 della Ragione. Pluralit\u00e0 delle Filosofie nel Medioevo. vol. II.1, p",
        "anno": "2012",
        "autori": "SACCENTI R"
      },
      "rawcontent": [
        "Contributo in volume (Capitolo o Saggio)",
        "SACCENTI R (2012). La d\u00e9finition de vertu chez les th\u00e9ologiens de la",
        "premi\u00e8re moiti\u00e9 du XIIIe si\u00e8cle. In: (a cura di): Musco A., Compagno C.,",
        "D'Agostino S., Musotto G. , Universalit\u00e0 della Ragione. Pluralit\u00e0 delle",
        "Filosofie nel Medioevo. vol. II.1, p. 219-226, PALERMO:Officina Studi",
        "Medievali, ISBN: 9788864850498"
      ],
      "anno": "2012"
    },
    {
      "id": "20",
      "type": "Contributo in volume (Capitolo o Saggio)",
      "parsed": {
        "precsp": "65-86",
        "titolo": "In unitate pacis sub Dei timore capientes. I caratteri delle missioni latine presso i Mongoli",
        "ISBN": [
          "9788812001040"
        ],
        "csp": "ROMA:Istituto della Enciclopedia Italiana Treccani, ISBN: 9788812001040",
        "opera": "(a cura di): Alberto Melloni, In via in saecula. La Bibbia di Marco Polo tra Europa e Cina. vol. 1, p",
        "anno": "2012",
        "autori": "SACCENTI R"
      },
      "rawcontent": [
        "Contributo in volume (Capitolo o Saggio)",
        "SACCENTI R (2012). In unitate pacis sub Dei timore capientes. I caratteri",
        "delle missioni latine presso i Mongoli. In: (a cura di): Alberto Melloni, In via",
        "in saecula. La Bibbia di Marco Polo tra Europa e Cina. vol. 1, p. 65-86,",
        "ROMA:Istituto della Enciclopedia Italiana Treccani, ISBN: 9788812001040"
      ],
      "anno": "2012"
    },
    {
      "id": "21",
      "type": "Contributo in volume (Capitolo o Saggio)",
      "parsed": {
        "precsp": "21-44",
        "titolo": "Il testo biblico e i marginalia della Bibbia di Marco Polo",
        "ISBN": [
          "9788812001040"
        ],
        "csp": "ROMA:Istituto della Enciclopedia Italiana Treccani, ISBN: 9788812001040",
        "opera": "(a cura di): Alberto Melloni, In via in saecula. La Bibbia di Marco Polo tra Europa e Cina. vol. 1, p",
        "anno": "2012",
        "autori": "SACCENTI R"
      },
      "rawcontent": [
        "Contributo in volume (Capitolo o Saggio)",
        "SACCENTI R (2012). Il testo biblico e i marginalia della Bibbia di Marco",
        "Polo. In: (a cura di): Alberto Melloni, In via in saecula. La Bibbia di Marco",
        "Polo tra Europa e Cina. vol. 1, p. 21-44, ROMA:Istituto della Enciclopedia",
        "Italiana Treccani, ISBN: 9788812001040"
      ],
      "anno": "2012"
    },
    {
      "id": "22",
      "type": "Voce (in dizionario o enciclopedia)",
      "parsed": {
        "titolo": "Mura Bonfiglio",
        "opera": "Dizionario Biografico degli Italiani. vol. 77, ROMA:Istituto della Enciclopedia Italiana Treccani",
        "anno": "2012",
        "autori": "SACCENTI R"
      },
      "rawcontent": [
        "Voce (in dizionario o enciclopedia)",
        "SACCENTI R (2012). Mura Bonfiglio. In: Dizionario Biografico degli Italiani.",
        "vol. 77, ROMA:Istituto della Enciclopedia Italiana Treccani"
      ],
      "anno": "2012"
    },
    {
      "id": "23",
      "type": "Articolo in rivista",
      "parsed": {
        "titolo": "La dottrina dell'uti e del frui di Ugo di Saint-Cher. Studio ed edizione della questio 35 del ms. Douai Bibl. Mun. 434, ff. 40ra-vb",
        "ISSN": [
          "1121-9343"
        ],
        "journal": "MEMORIE DOMENICANE",
        "csp": "vol. 42, p. 81-132, ISSN: 1121-9343",
        "anno": "2011",
        "autori": "Saccenti R"
      },
      "rawcontent": [
        "Articolo in rivista",
        "Saccenti R (2011). La dottrina dell'uti e del frui di Ugo di Saint-Cher. Studio",
        "ed edizione della questio 35 del ms. Douai Bibl. Mun. 434, ff. 40ra-vb.",
        "MEMORIE DOMENICANE, vol. 42, p. 81-132, ISSN: 1121-9343"
      ],
      "anno": "2011"
    },
    {
      "id": "24",
      "type": "Articolo in rivista",
      "parsed": {
        "titolo": "Il sapere storico-religioso nel Novecento",
        "ISSN": [
          "1828-7743"
        ],
        "journal": "CONVIVIUM ASSISIENSE",
        "csp": "vol. 13, p. 39-55, ISSN: 1828-7743",
        "anno": "2011",
        "autori": "SACCENTI R"
      },
      "rawcontent": [
        "Articolo in rivista",
        "SACCENTI R (2011). Il sapere storico-religioso nel Novecento.",
        "CONVIVIUM ASSISIENSE, vol. 13, p. 39-55, ISSN: 1828-7743"
      ],
      "anno": "2011"
    },
    {
      "id": "25",
      "type": "Articolo in rivista",
      "parsed": {
        "titolo": "\u00c0 propos de la datation d\u2019un t\u00e9moin de la morale aristot\u00e9licienne du XIIIe si\u00e8cle : le Compendium philosophiae : rappel historiographique et orientations de recherche",
        "ISSN": [
          "2257-6819"
        ],
        "journal": "SPICAE (EN LIGNE)",
        "csp": "vol. 1, p. 79-94, ISSN: 2257-6819",
        "anno": "2011",
        "autori": "SACCENTI R"
      },
      "rawcontent": [
        "Articolo in rivista",
        "SACCENTI R (2011). \u00c0 propos de la datation d\u2019un t\u00e9moin de la morale",
        "aristot\u00e9licienne du XIIIe si\u00e8cle : le Compendium philosophiae : rappel",
        "historiographique et orientations de recherche. SPICAE (EN LIGNE), vol. 1,",
        "p. 79-94, ISSN: 2257-6819"
      ],
      "anno": "2011"
    },
    {
      "id": "26",
      "type": "Contributo in volume (Capitolo o Saggio)",
      "parsed": {
        "precsp": "273-303",
        "titolo": "Descrizione dei manoscritti del \"De Servorum Dei beatificatione et Beatorum canonizatione\" della Biblioteca Universitaria di Bologna",
        "ISBN": [
          "978-88-6372-357-1"
        ],
        "csp": "ROMA:Edizioni di Storia e Letteratura, ISBN: 978-88-6372-357-1",
        "opera": "(a cura di): Fattori MT, Le fatiche di Benedetto XIV. Saggi sulla trattatistica di Papa Lambertini. p",
        "anno": "2011",
        "autori": "Saccenti R"
      },
      "rawcontent": [
        "Contributo in volume (Capitolo o Saggio)",
        "Saccenti R (2011). Descrizione dei manoscritti del \"De Servorum Dei",
        "beatificatione et Beatorum canonizatione\" della Biblioteca Universitaria di",
        "Bologna. In: (a cura di): Fattori MT, Le fatiche di Benedetto XIV. Saggi sulla",
        "trattatistica di Papa Lambertini. p. 273-303, ROMA:Edizioni di Storia e",
        "Letteratura, ISBN: 978-88-6372-357-1"
      ],
      "anno": "2011"
    },
    {
      "id": "27",
      "type": "Contributo in volume (Capitolo o Saggio)",
      "parsed": {
        "precsp": "173-192",
        "titolo": "L'evoluzione della nozione di \"theologia\" negli scritti dei \"magistri\" parigini fra gli anni '20 e '40 del XIII secolo",
        "ISBN": [
          "978-88-4673-090-9"
        ],
        "csp": "PISA:ETS, ISBN: 978-88-4673-090-9",
        "opera": "(a cura di): Perfetti S, \"Scientia, Fides, Theologia\". Studi di filosofia medievale in onore di Gianfranco Fioravanti. p",
        "anno": "2011",
        "autori": "Saccenti R"
      },
      "rawcontent": [
        "Contributo in volume (Capitolo o Saggio)",
        "Saccenti R (2011). L'evoluzione della nozione di \"theologia\" negli scritti dei",
        "\"magistri\" parigini fra gli anni '20 e '40 del XIII secolo. In: (a cura di): Perfetti",
        "S, \"Scientia, Fides, Theologia\". Studi di filosofia medievale in onore di",
        "Gianfranco Fioravanti. p. 173-192, PISA:ETS, ISBN: 978-88-4673-090-9"
      ],
      "anno": "2011"
    },
    {
      "id": "28",
      "type": "Contributo in volume (Capitolo o Saggio)",
      "parsed": {
        "precsp": "319-336",
        "titolo": "Materiali preparatori per l'edizione dell'edizione romana a cura di E. de Azevedo",
        "ISBN": [
          "978-88-6372-357-1"
        ],
        "csp": "ISBN: 978-88-6372-357-1",
        "opera": "(a cura di): Fattori MT, Le fatiche di Benedetto XIV. Saggi sulla trattatistica di Benedetto XIV. p",
        "anno": "2011",
        "autori": "Saccenti R"
      },
      "rawcontent": [
        "Contributo in volume (Capitolo o Saggio)",
        "Saccenti R (2011). Materiali preparatori per l'edizione dell'edizione romana",
        "a cura di E. de Azevedo. In: (a cura di): Fattori MT, Le fatiche di Benedetto",
        "XIV. Saggi sulla trattatistica di Benedetto XIV. p. 319-336, ISBN:",
        "978-88-6372-357-1"
      ],
      "anno": "2011"
    },
    {
      "id": "29",
      "type": "Contributo in volume (Capitolo o Saggio)",
      "parsed": {
        "precsp": "305-318",
        "titolo": "Carteggi lambertiniani per l'edizione dei trattati",
        "ISBN": [
          "978-88-6372-357-1"
        ],
        "csp": "ROMA:Edizioni di Storia e Letteratura, ISBN: 978-88-6372-357-1",
        "opera": "(a cura di): Fattori MT, Le fatiche di Benedetto XIV. Saggi sulla trattatistica di Papa Lambertini. p",
        "anno": "2011",
        "autori": "Saccenti R"
      },
      "rawcontent": [
        "Contributo in volume (Capitolo o Saggio)",
        "Saccenti R (2011). Carteggi lambertiniani per l'edizione dei trattati. In: (a",
        "cura di): Fattori MT, Le fatiche di Benedetto XIV. Saggi sulla trattatistica di",
        "Papa Lambertini. p. 305-318, ROMA:Edizioni di Storia e Letteratura, ISBN:",
        "978-88-6372-357-1"
      ],
      "anno": "2011"
    },
    {
      "id": "30",
      "type": "Contributo in volume (Capitolo o Saggio)",
      "parsed": {
        "precsp": "139-170",
        "titolo": "Il \"De Servorum Dei beatificatione et Beatorum canonizatione\" di Prospero Lambertini, papa Benedetto XIV: materiali per una ricerca",
        "ISBN": [
          "978-88-6372-357-1"
        ],
        "csp": "ROMA:Edizioni di Storia e Letteratura, ISBN: 978-88-6372-357-1",
        "opera": "(a cura di): Fattori MT, Le fatiche di Benedetto XIV. Saggi sulla trattatistica di Papa Lambertini. p",
        "anno": "2011",
        "autori": "Saccenti R"
      },
      "rawcontent": [
        "Contributo in volume (Capitolo o Saggio)",
        "Saccenti R (2011). Il \"De Servorum Dei beatificatione et Beatorum",
        "canonizatione\" di Prospero Lambertini, papa Benedetto XIV: materiali per",
        "una ricerca. In: (a cura di): Fattori MT, Le fatiche di Benedetto XIV. Saggi",
        "sulla trattatistica di Papa Lambertini. p. 139-170, ROMA:Edizioni di Storia e",
        "Letteratura, ISBN: 978-88-6372-357-1"
      ],
      "anno": "2011"
    },
    {
      "id": "31",
      "type": "Contributo in volume (Capitolo o Saggio)",
      "parsed": {
        "precsp": "57-101",
        "titolo": "La lunga genesi dell'opera sulle canonizzazioni",
        "ISBN": [
          "978-88-6372-357-1"
        ],
        "csp": "ROMA:Edizioni di Storia e Letteratura, ISBN: 978-88-6372-357-1",
        "opera": "(a cura di): Fattori MT, Le fatiche di Benedetto XIV. Saggi sulla trattatistica di Papa Lambertini. p",
        "anno": "2011",
        "autori": "Saccenti R"
      },
      "rawcontent": [
        "Contributo in volume (Capitolo o Saggio)",
        "Saccenti R (2011). La lunga genesi dell'opera sulle canonizzazioni. In: (a",
        "cura di): Fattori MT, Le fatiche di Benedetto XIV. Saggi sulla trattatistica di",
        "Papa Lambertini. p. 57-101, ROMA:Edizioni di Storia e Letteratura, ISBN:",
        "978-88-6372-357-1"
      ],
      "anno": "2011"
    },
    {
      "id": "32",
      "type": "Articolo in rivista",
      "parsed": {
        "titolo": "La \"Summa Alexandrinorum\". Storia e contenuto di un'epitome dell'Etica Nicomachea",
        "ISSN": [
          "1370-7493"
        ],
        "journal": "RECHERCHES DE TH\u00c9OLOGIE ET PHILOSOPHIE M\u00c9DI\u00c9VALES",
        "csp": "vol. 77, p. 201-234, ISSN: 1370-7493",
        "anno": "2010",
        "autori": "Saccenti R"
      },
      "rawcontent": [
        "Articolo in rivista",
        "Saccenti R (2010). La \"Summa Alexandrinorum\". Storia e contenuto di",
        "un'epitome dell'Etica Nicomachea. RECHERCHES DE TH\u00c9OLOGIE ET",
        "PHILOSOPHIE M\u00c9DI\u00c9VALES, vol. 77, p. 201-234, ISSN: 1370-7493"
      ],
      "anno": "2010"
    },
    {
      "id": "33",
      "type": "Articolo in rivista",
      "parsed": {
        "titolo": "\"Quidam dicunt quod aqua sive ablutio, quidam quod caracter\". Discussioni sulla natura del battesimo fra la met\u00e0 del XII e i primi decenni del XIII secolo",
        "ISSN": [
          "0393-3598"
        ],
        "journal": "CRISTIANESIMO NELLA STORIA",
        "csp": "vol. 31, p. 93-123, ISSN: 0393-3598",
        "anno": "2010",
        "autori": "Saccenti R"
      },
      "rawcontent": [
        "Articolo in rivista",
        "Saccenti R (2010). \"Quidam dicunt quod aqua sive ablutio, quidam quod",
        "caracter\". Discussioni sulla natura del battesimo fra la met\u00e0 del XII e i primi",
        "decenni del XIII secolo. CRISTIANESIMO NELLA STORIA, vol. 31, p.",
        "93-123, ISSN: 0393-3598"
      ],
      "anno": "2010"
    },
    {
      "id": "34",
      "type": "Articolo in rivista",
      "parsed": {
        "titolo": "Quattro gradi di virt\u00f9: il modello etico dei Commentarii di Macrobio nel XII secolo",
        "ISSN": [
          "0391-2566"
        ],
        "journal": "MEDIOEVO: RIVISTA DI STORIA DELLA FILOSOFIA MEDIEVALE",
        "csp": "vol. 31, p. 69-101, ISSN: 0391-2566",
        "anno": "2006",
        "autori": "SACCENTI R"
      },
      "rawcontent": [
        "Articolo in rivista",
        "SACCENTI R (2006). Quattro gradi di virt\u00f9: il modello etico dei",
        "Commentarii di Macrobio nel XII secolo. MEDIOEVO: RIVISTA DI STORIA",
        "DELLA FILOSOFIA MEDIEVALE, vol. 31, p. 69-101, ISSN: 0391-2566"
      ],
      "anno": "2006"
    }
  ],
  "pubbs": [
    {
      "id": "1",
      "type": "Articolo in rivista",
      "parsed": {
        "titolo": "Stefano Langton sul battesimo. Edizione delle Quaestiones",
        "ISSN": [
          "0391-2566"
        ],
        "journal": "MEDIOEVO: RIVISTA DI STORIA DELLA FILOSOFIA MEDIEVALE",
        "csp": "vol. 40, p. 197-264, ISSN: 0391-2566",
        "anno": "2016",
        "autori": "SACCENTI R"
      },
      "rawcontent": [
        "Articolo in rivista",
        "SACCENTI R (2016). Stefano Langton sul battesimo. Edizione delle",
        "Quaestiones. MEDIOEVO: RIVISTA DI STORIA DELLA FILOSOFIA",
        "MEDIEVALE, vol. 40, p. 197-264, ISSN: 0391-2566"
      ],
      "anno": "2016"
    },
    {
      "id": "2",
      "type": "Contributo in volume (Capitolo o Saggio)",
      "parsed": {
        "precsp": "32-44",
        "titolo": "The decree Exivi de Paradiso and its implications for mendicant poverty",
        "ISBN": [
          "978-1-4724-3732-7"
        ],
        "csp": "LONDON-NEW YORK:Routledge Taylor & Francis Group, ISBN: 978-1-4724-3732-7",
        "opera": "(a cura di): MEWS CJ; WELCH A, Poverty and Devotion in Mendicant Cultures. 1200-1450. p",
        "anno": "2016",
        "autori": "SACCENTI R"
      },
      "rawcontent": [
        "Contributo in volume (Capitolo o Saggio)",
        "SACCENTI R (2016). The decree Exivi de Paradiso and its implications for",
        "mendicant poverty. In: (a cura di): MEWS CJ; WELCH A, Poverty and",
        "Devotion in Mendicant Cultures. 1200-1450. p. 32-44, LONDON-NEW",
        "YORK:Routledge Taylor & Francis Group, ISBN: 978-1-4724-3732-7"
      ],
      "anno": "2016"
    },
    {
      "id": "3",
      "type": "Monografia o trattato scientifico",
      "parsed": {
        "precsp": "1-170",
        "titolo": "Debetaing Medieval Natural Law: A Survey. p",
        "ISBN": [
          "978-0-268-10040-7"
        ],
        "csp": "NOTRE DAME, IND.:University of Notre Dame Press, ISBN: 978-0-268-10040-7",
        "anno": "2016",
        "autori": "SACCENTI R"
      },
      "rawcontent": [
        "Monografia o trattato scientifico",
        "SACCENTI R (2016). Debetaing Medieval Natural Law: A Survey. p. 1-170,",
        "NOTRE DAME, IND.:University of Notre Dame Press, ISBN:",
        "978-0-268-10040-7"
      ],
      "anno": "2016"
    },
    {
      "id": "4",
      "type": "Articolo in rivista",
      "parsed": {
        "titolo": "Faith and connexio virtutum in the Treatise of the Theological Virtues in the First Theological Summas (1220s-1240s)",
        "ISSN": [
          "1612-3964"
        ],
        "journal": "ARCHA VERBI",
        "csp": "vol. 12, p. 221-235, ISSN: 1612-3964",
        "anno": "2014",
        "autori": "SACCENTI R"
      },
      "rawcontent": [
        "Articolo in rivista",
        "SACCENTI R (2014). Faith and connexio virtutum in the Treatise of the",
        "Theological Virtues in the First Theological Summas (1220s-1240s).",
        "ARCHA VERBI, vol. 12, p. 221-235, ISSN: 1612-3964"
      ],
      "anno": "2014"
    },
    {
      "id": "5",
      "type": "Articolo in rivista",
      "parsed": {
        "titolo": "THE MATERIA SUPER LIBROS SENTENTIARUM ATTRIBUTED TO PETER COMESTOR: STUDY OF THE TEXT AND CRITICAL EDITION",
        "ISSN": [
          "0068-4023"
        ],
        "journal": "BULLETIN DE PHILOSOPHIE MEDIEVALE",
        "csp": "vol. 54, p. 155-215, ISSN: 0068-4023",
        "anno": "2013",
        "autori": "SACCENTI R"
      },
      "rawcontent": [
        "Articolo in rivista",
        "SACCENTI R (2013). THE MATERIA SUPER LIBROS SENTENTIARUM",
        "ATTRIBUTED TO PETER COMESTOR: STUDY OF THE TEXT AND",
        "CRITICAL EDITION. BULLETIN DE PHILOSOPHIE MEDIEVALE, vol. 54,",
        "p. 155-215, ISSN: 0068-4023"
      ],
      "anno": "2013"
    },
    {
      "id": "6",
      "type": "Contributo in volume (Capitolo o Saggio)",
      "parsed": {
        "precsp": "275-293",
        "titolo": "Questions et Sentences: l'enseignement entre la fin du XIIe et le d\u00e9but du XIIIe si\u00e8cle",
        "ISBN": [
          "978-2-503-55154-8"
        ],
        "ISSN": [
          "2032-1252"
        ],
        "csp": "TURNHOUT:Brepols, ISBN: 978-2-503-55154-8, ISSN: 2032-1252",
        "opera": "(a cura di): VERGER J., WEIJERS O., Les d\u00e9buts de l'enseignement universitaire \u00e0 Paris (1200-1245 environ). STUDIA ARTISTARUM, vol. 38, p",
        "anno": "2013",
        "autori": "SACCENTI R"
      },
      "rawcontent": [
        "Contributo in volume (Capitolo o Saggio)",
        "SACCENTI R (2013). Questions et Sentences: l'enseignement entre la fin",
        "du XIIe et le d\u00e9but du XIIIe si\u00e8cle. In: (a cura di): VERGER J., WEIJERS",
        "O., Les d\u00e9buts de l'enseignement universitaire \u00e0 Paris (1200-1245 environ).",
        "STUDIA ARTISTARUM, vol. 38, p. 275-293, TURNHOUT:Brepols, ISBN:",
        "978-2-503-55154-8, ISSN: 2032-1252"
      ],
      "anno": "2013"
    },
    {
      "id": "7",
      "type": "Contributo in volume (Capitolo o Saggio)",
      "parsed": {
        "precsp": "359-469",
        "titolo": "Concilium Viennense 1311-1312",
        "ISBN": [
          "978-2-503-52527-3"
        ],
        "ISSN": [
          "0589-7963"
        ],
        "csp": "TURNHOUT:Brepols, ISBN: 978-2-503-52527-3, ISSN: 0589-7963",
        "opera": "(a cura di): ALBERIGO G., MELLONI A., Conciliorum Oecumenicorum Generaliumque Decreta II/!. CORPUS CHRISTIANORUM. CONTINUATIO MEDIAEVALIS, vol. II/1, p",
        "anno": "2013",
        "autori": "SACCENTI R"
      },
      "rawcontent": [
        "Contributo in volume (Capitolo o Saggio)",
        "SACCENTI R (2013). Concilium Viennense 1311-1312. In: (a cura di):",
        "ALBERIGO G., MELLONI A., Conciliorum Oecumenicorum Generaliumque",
        "Decreta II/!. CORPUS CHRISTIANORUM. CONTINUATIO MEDIAEVALIS,",
        "vol. II/1, p. 359-469, TURNHOUT:Brepols, ISBN: 978-2-503-52527-3,",
        "ISSN: 0589-7963"
      ],
      "anno": "2013"
    },
    {
      "id": "8",
      "type": "Monografia o trattato scientifico",
      "parsed": {
        "precsp": "1-248",
        "titolo": "CONSERVARE LA RETTA VOLONTA'. L'ATTO MORALE NELLE DOTTRINE DI FILIPPO IL CANCELLIERE E UGO SI SAINT-CHER (1225-1235). vol. 1, p",
        "ISBN": [
          "978-88-15-24453-6"
        ],
        "csp": "BOLOGNA:Il Mulino, ISBN: 978-88-15-24453-6",
        "anno": "2013",
        "autori": "SACCENTI R"
      },
      "rawcontent": [
        "Monografia o trattato scientifico",
        "SACCENTI R (2013). CONSERVARE LA RETTA VOLONTA'. L'ATTO",
        "MORALE NELLE DOTTRINE DI FILIPPO IL CANCELLIERE E UGO SI",
        "SAINT-CHER (1225-1235). vol. 1, p. 1-248, BOLOGNA:Il Mulino, ISBN:",
        "978-88-15-24453-6"
      ],
      "anno": "2013"
    },
    {
      "id": "9",
      "type": "Articolo in rivista",
      "parsed": {
        "titolo": "\"Quidam dicunt quod aqua sive ablutio, quidam quod caracter\". Discussioni sulla natura del battesimo fra la met\u00e0 del XII e i primi decenni del XIII secolo",
        "ISSN": [
          "0393-3598"
        ],
        "journal": "CRISTIANESIMO NELLA STORIA",
        "csp": "vol. 31, p. 93-123, ISSN: 0393-3598",
        "anno": "2010",
        "autori": "Saccenti R"
      },
      "rawcontent": [
        "Articolo in rivista",
        "Saccenti R (2010). \"Quidam dicunt quod aqua sive ablutio, quidam quod",
        "caracter\". Discussioni sulla natura del battesimo fra la met\u00e0 del XII e i primi",
        "decenni del XIII secolo. CRISTIANESIMO NELLA STORIA, vol. 31, p.",
        "93-123, ISSN: 0393-3598"
      ],
      "anno": "2010"
    },
    {
      "id": "10",
      "type": "Articolo in rivista",
      "parsed": {
        "titolo": "La \"Summa Alexandrinorum\". Storia e contenuto di un'epitome dell'Etica Nicomachea",
        "ISSN": [
          "1370-7493"
        ],
        "journal": "RECHERCHES DE TH\u00c9OLOGIE ET PHILOSOPHIE M\u00c9DI\u00c9VALES",
        "csp": "vol. 77, p. 201-234, ISSN: 1370-7493",
        "anno": "2010",
        "autori": "Saccenti R"
      },
      "rawcontent": [
        "Articolo in rivista",
        "Saccenti R (2010). La \"Summa Alexandrinorum\". Storia e contenuto di",
        "un'epitome dell'Etica Nicomachea. RECHERCHES DE TH\u00c9OLOGIE ET",
        "PHILOSOPHIE M\u00c9DI\u00c9VALES, vol. 77, p. 201-234, ISSN: 1370-7493"
      ],
      "anno": "2010"
    }
  ],
  "general": {
    "settore": "11/C5",
    "progr": "33564",
    "nome": "SACCENTI Riccardo",
    "fascia": "Seconda"
  },
  "titoli": {
    "Direzione o partecipazione a comitati editoriali di riviste, collane editoriali, enciclopedie e": [
      {
        "content": "Partecipazione alla redazione della rivista \"Cristianesimo nella storia\"",
        "periodo": "dal 01-11-2008 a oggi"
      },
      {
        "content": "Revisore di articoli per la \"Revue d'histoire ecclesiastique\"",
        "periodo": "dal 01-06-2015 a oggi"
      },
      {
        "content": "Revisore di articoli per la rivista \"Villa I Tatti Studies\"",
        "periodo": "dal 01-07-2016 a oggi"
      }
    ],
    "Organizzazione o partecipazione come relatore a convegni di carattere scientifico in Italia": [
      {
        "content": "Partecipazione con la relazione \"La discussione sul libero arbitrio nel Commento alle Sentenze di Ugo di St. Cher\" alla giornata di studio \"L'edizione critica dei testi medievali filosofici e teologici\", Padova",
        "periodo": "dal 14-11-2006 al 15-11-2006"
      },
      {
        "content": "Partecipazione con la relazione \"La d\u00e9finition de vertu chez les th\u00e9ologien de la premi\u00e8ere moiti\u00e9 du XIIIe si\u00e8cle\" al \"12th International Congress of Medieval Philosophy. Soci\u00e9t\u00e9 Internationale pour l'\u00e9tude de la Philosophie M\u00e9di\u00e9vale\", Palermo",
        "periodo": "dal 16-09-2007 al 22-09-2007"
      },
      {
        "content": "Partecipazione con la relazione \"Le Quaestiones di Stefano Langton sul battesimo\" alle giornate di studio \"L'edizione critica dei testi medievali filosofici e teologici\", Padova",
        "periodo": "dal 24-11-2008 al 25-11-2008"
      },
      {
        "content": "Organizzazione del convegno internazionale \"Ad Imaginem Dei. Foundations and objections within the discourse on human dignty\", Bologna - Rossena (RE)",
        "periodo": "dal 16-07-2009 al 18-07-2009"
      },
      {
        "content": "Partecipazione con la relazione \"The Imago Dei in scholastic Theology (XIIth-XIIIth centuries)\" al convegno \"Ad Imaginem Dei. Foundations and objections within the discourse on human dignity\", Bologna-Rossena (RE)",
        "periodo": "dal 16-07-2009 al 18-07-2009"
      },
      {
        "content": "Partecipazione con la relazione \"Cognitio veritatis. La M\u00e9taphysique et l'Ethique d'Aristote comme sources de l'anonyme Compendium philosophiae (moiti\u00e9 du XIIIe si\u00e8cle)\" al convegno \"Auctor et auctoritas in Latinis Medii Aevi litteris. VI Convegno dell'International Medieval Commettee\", Napoli - Benevento",
        "periodo": "dal 10-11-2010 al 13-11-2010"
      },
      {
        "content": "Partecipazione con la relazione \"L'arriv\u00e9e de l'Ethique \u00e0 Nicomaque dans la culture latine m\u00e9di\u00e9vale\" al \"Cycle de conf\u00e9rence du Centre de M\u00e9di\u00e9vistique Jean Schneider\", Nancy (France)",
        "periodo": "dal 07-12-2010 al 07-12-2010"
      },
      {
        "content": "Organizzazione del convegno internazioanle \"Attorno alla Bibbia di Marco Polo\", Firenze, Biblioteca Medicea Laurenziana",
        "periodo": "dal 06-04-2011 al 06-04-2011"
      },
      {
        "content": "Partecipazione con la relazione \"La Bibbia di Marco Polo, studi biblici, ordini mendicanti e missioni in oriente nel XIII secolo\" al convengo \"Attorno alla Bibbia di Marco Polo\", Firenze, Biblioteca Medicea Laurenziana",
        "periodo": "dal 06-04-2011 al 06-04-2011"
      },
      {
        "content": "Organizzazione del ciclo di conferenze \"Cina e Cristianesimo dall'VIII secolo ad oggi\", Prato, Biblioteca A. Lazzerini",
        "periodo": "dal 01-05-2011 al 31-10-2011"
      },
      {
        "content": "Partecipazione con la relazione \"Un libro lungo le vie della seta. La Bibbia di Marco Polo\" al ciclo di seminari \"Cina e Cristianesimo dall'VIII secolo ad oggi\", Prato, Biblioteca A. Lazzerini",
        "periodo": "dal 09-06-2011 al 09-06-2011"
      },
      {
        "content": "Partecipazione con la relzione \"The Treatise of the Theological Virtues in the first Theological Summas (William of Auxerre / Philip the Chancellor / Hugues of Saint Cher)\" al convegno \"Fides Virtus. The Virtue of Faith in the Context of the Theological Virtues. Exegesis, Moral Theology and Pastoral Care from 12th to Early 16th Century\", IGTM (Internationale Gesellschaft f\u00fcr Theologische Medi\u00e4vistik), Padova",
        "periodo": "dal 06-07-2011 al 09-07-2011"
      },
      {
        "content": "Partecipazione con la relazione \"Novit\u00e0, tradizione e pluralit\u00e0 di culture. I fondamenti del progetto culturale di Pico della Mirandola nella Oratio de hominis dignitate\" al ciclo di seminari \"Cina e Cristianesimo dall'VIII secolo ad oggi\", Prato, Biblioteca A. Lazzerini",
        "periodo": "dal 15-10-2011 al 15-10-2011"
      },
      {
        "content": "Partecipazione con la relazione \"Bologne, Toulouse et la formation d'une culture philosophique europ\u00e9enne au XIIIe si\u00e8cle: la contribution de ma\u00eetre Roland de Cremone, fr\u00e8re precheure\" al \"Bologne - Toulouse. 30 ans de jumelage\", Toulouse",
        "periodo": "dal 21-11-2011 al 26-11-2011"
      },
      {
        "content": "Partecipazione con la relazione \"The Decree Exivi de Paradiso and its Implications for Mendicant Poverty\" al convegno \"Mendicant Culture and Devotion in Italy. 1250-1450\", Prato, Monash Center",
        "periodo": "dal 05-12-2011 al 05-12-2011"
      },
      {
        "content": "Partecipazione con la relazione \"Le fonti del De Servorum Dei e il loro uso nel trattato lambertiniano\" al convegno \"Storia, medicina e diritto nei trattati di Prospero Lambertini - Benedetto XIV\", Modena - Bologna",
        "periodo": "dal 12-12-2011 al 13-12-2011"
      },
      {
        "content": "Partecipazione con la relazione \"Storia della redazione della Dei Verbum\" alla settimana teologica di ATI e ABI \"La Bibbia e la vita della Chiesa. La Costituzione Dei Verbum a 50 anni dal Concilio Vaticano II\", Monastero di Camaldoli (Poppi, AR)",
        "periodo": "dal 06-08-2012 al 11-08-2012"
      },
      {
        "content": "Partecipazione con la relazione \"The Bible of Marco Polo (13th - 18th centuries)\" al \"11th International Symposium, History of the Church in China. From its beginnings to the Scheut Fathers and 20th Century. Unveiling some less known sources, sounds and pictures\", Leuven",
        "periodo": "dal 04-09-2012 al 07-09-2012"
      },
      {
        "content": "Partecipazione con la relazione \"Senteces et Questions: l'enseignement entre la fin du XIIe et le d\u00e9but du XIIIe si\u00e8cle\" al convegno \"Les d\u00e9buts de l'enseignement universitaire \u00e0 Paris (1200-1245 environs)\", organizzato da O. Weijers e J. Verger, Paris, I.R.H.T.",
        "periodo": "dal 13-09-2012 al 14-09-2012"
      },
      {
        "content": "Partecipazione con la relazione \"I Quatuor libri Sententiarum di Pietro Lombardo nella cultura europea fra XII e primo XIII secolo\" al seminario di studio \"Filosofia, teologia ed esegesi tra XII e XIII secolo: aspetti filologici e dottrinali\", Padova",
        "periodo": "dal 06-11-2012 al 06-11-2012"
      },
      {
        "content": "Partecipazione con la relazione \"History and Features of the Manuscript Pluteo III, capsula 1 of the Laurentian Library of Florence\" all'inaugurazione della mostra \"In via. In saecula\", Pechino, Universit\u00e0 di Pechino",
        "periodo": "dal 11-05-2013 al 11-05-2013"
      },
      {
        "content": "Partecipazione con la relazione \"Ad Gentes: storia della redazione\" alla settimana teologica dell'ATI \"Comunicare la fede. I decreti Ad Gentes e Inter mirifica del Concilio Vaticano II\", Monastero di Camaldoli (Poppi, AR)",
        "periodo": "dal 04-08-2013 al 09-08-2013"
      },
      {
        "content": "Partecipazione con la relazione \"La distinctio prima di Graziano e la codificazione dello ius canonicum fra XV e XVI secolo\" al convegno \"Legge e Natura. I dibattiti teologici e giuridici fra XV e XVII secolo\", Modena - Bologna",
        "periodo": "dal 28-11-2013 al 29-11-2013"
      },
      {
        "content": "Organizzazione del convegno \"Legge e Natura. I dibattiti teologici e giuridici fra XV e XVII secolo\", Modena - Bologna",
        "periodo": "dal 28-11-2013 al 29-11-2013"
      },
      {
        "content": "Partecipazione con la relazione \"Constantine in Question. The Construction of the Ideal Figure of the Emperor in the Beginning of the 14th Century\" al convegno \"Constantine and the Grandeur that was Rome. An Interdisciplinary Symposium\", Oxford, Kellog College, University of Oxford",
        "periodo": "dal 11-12-2013 al 12-12-2013"
      },
      {
        "content": "Partecipazione con la relazione \"Preyers, Saints, an Images. The Suppression of Superstition in the Libellus ad Leonem X\" al convegno \"Arts, Portraits and Representation in the Reformation Era. 4th RefoRC Conference\", Bologna",
        "periodo": "dal 15-05-2014 al 17-05-2014"
      },
      {
        "content": "Partecipazione con la relazione \"The COGD Program: A Critical Update\" al congeno internazionale \"International Medieval Congress 2015\", Leeds",
        "periodo": "dal 06-07-2015 al 09-07-2015"
      },
      {
        "content": "Partecipazione con la relazione \"Niola Pistelli\" al convegno \"Il Chiostro dei folli di Dio\", Scandicci (FI)",
        "periodo": "dal 24-10-2015 al 25-10-2015"
      },
      {
        "content": "Organizzazione del convegno \"Il Chiostro dei Folli di Dio\", Scandicci (FI)",
        "periodo": "dal 24-10-2015 al 25-10-2015"
      },
      {
        "content": "Partecipazione con la relazione \"Obiecit Joachim abbas magistro: the Fourth Lateran Council, the Critics of Joachim of Fiore to Peter Lombard and the Masters of Paris\" al convegno internazionale \"Concilium Lateranense IV. Commemorating the Octocentenary of the Fourth Lateran Council of 1215\", Roma",
        "periodo": "dal 23-11-2015 al 29-11-2015"
      },
      {
        "content": "Organizzazione del convegno internazionale \"Renaissance Religion II: Modes and Meanings in History\", Bologna",
        "periodo": "dal 09-06-2016 al 10-06-2016"
      },
      {
        "content": "Partecipazione con la relazione \"The Sripture and the Saints: Nicholaus Manerbi's Vernacular Translations and the Reform of the Church\" al convengo internazionale \"Renaissance Religion II: Modes and Meanings in History\", Bologna",
        "periodo": "dal 09-06-2016 al 10-06-2016"
      },
      {
        "content": "Partecipazione con la relazione \"Teologia, prassi ecclesiale e ragioni della fede: il ruolo dei maestri\" al convegno \"Una scuola di teologia per laici. Le Settimane di cultura religiosa di Camaldoli nella storia della Chiesa e della societ\u00e0 italiana (1936-1946)\", Monastero di Camaldoli (Poppi, AR)",
        "periodo": "dal 25-08-2016 al 25-08-2016"
      },
      {
        "content": "Partecipazione con la relazione \"Illuminare la mente dell'uomo. Le idee divine nei primi maestri francescani (Alessandro di Hales e Giovanni de La Rochelle)\" al convegno \"La dottrina delle idee nel pensiero francescano del XIII-XIV secolo\", Trento",
        "periodo": "dal 27-10-2016 al 27-10-2016"
      },
      {
        "content": "Partecipazione con la relazione \"Il sogno della santit\u00e0 e l'imposizione del chiostro: Giovanni Vannucci e l'esperienza di Nomadelfia\" al convengo \"In santit\u00e0 ostinata e contraria. Don Zeno e i matti di Dio\", Mirandola (MO)",
        "periodo": "dal 26-11-2016 al 26-11-2016"
      }
    ],
    "Responsabilita' di studi e ricerche scientifiche affidati da qualificate istituzioni pubbliche o": [
      {
        "content": "STUDIO DELLA GENESI E DEI CONTENUTI DEL \"DE SERVORUM DEI BEATIFICATIONE ET BEATORUM CANONIZATIONE\" DI BENEDETTO XIV - INCARICO RICEVUTO DALLA FONDAZIONE PER LE SCIENZE RELIGIOSE GIOVANNI XXIII (BOLOGNA, ITALY)",
        "periodo": "dal 01-11-2008 al 30-09-2009"
      },
      {
        "content": "STUDIO DELLA SEZIONE DI METAFISICA ED ETICA DI UN ANONIMO \"COMPENDIUM PHILOSOPHIAE\" DELLA META' DEL XIII SECOLO E PREPARAZIONE DELLA EDIZIONE CRITICA DEL TESTO - PRESSO LA ERL 7229 MOYEN-AGE, ATELIER VINCENT DE BEAUVAIS: ENCYCLOPEDISME ET TRANSMISSION DES CONNAISSANCE, UNIVERSITE' NANCY2, FRANCE",
        "periodo": "dal 01-10-2009 al 30-09-2010"
      },
      {
        "content": "STUDIO DELLE CARATTERISTICHE CODICOLOGICHE E PALEOGRAFICHE DELLA \"BIBBIA DI MARCO POLO\" E DEL RAPPORTO FRA EUROPA CRISTIANA E IMPERO MONGOLO NEL XIII-XIV SECOLO - PRESSO LA FONDAZIONE PER LE SCIENZE RELIGIOSE GIOVANNI XXIII (BOLOGNA, ITALY)",
        "periodo": "dal 01-10-2010 al 14-01-2012"
      },
      {
        "content": "STUDIO DELLA PRASSI DI COMMENTO ALLE SENTENZE DI PIETRO LOMBARDO FRA 1150 E 1250 - PRESSO IL MEDIEVAL INSTITUTE, UNIVERSITY OF NOTRE DAME (U.S.A.)",
        "periodo": "dal 15-01-2012 al 15-05-2012"
      },
      {
        "content": "STUDIO DELLA STORIA DELLA NOZIONE DI LEGGE DI NATURA NEL PENSIERO FILOSOFICO E TEOLOGICO MEDIEVALE - PRESSO LA FONDAZIONE PER LE SCIENZE RELIGIOSE GIOVANNI XXIII (BOLOGNA, ITALY)",
        "periodo": "dal 15-05-2012 al 31-05-2016"
      },
      {
        "content": "STUDIO DELLA GENESI E DELL'INFLUENZA DEI \"DIALOGHI\" DI ALESSANDRO DI HAVELBERG - PRESSO L'ISTITUTO PER LA STORIA DELL'EUROPA MEDIETERRANEA (CNR, CAGLIARI)",
        "periodo": "dal 01-06-2016 a oggi"
      }
    ],
    "Specifiche esperienze professionali caratterizzate da attivita' di ricerca attinenti al settore": [
      {
        "content": "Research fellowship presso il Dipartimento di Filosofia dell'Universit\u00e0 di Pisa per la preparazione di dispense universitarie per il corso di Storia della filosofia medievale",
        "periodo": "dal 01-04-2001 al 30-04-2001"
      },
      {
        "content": "Research fellowship presso il Dipartimento di Filosofia dell'Universit\u00e0 di Pisa per la preparazione di dispense universitarie nell'ambito del corso di Storia della Filosofia Medievale",
        "periodo": "dal 01-02-2002 al 31-03-2002"
      },
      {
        "content": "Research fellowship presso il Dipartimento di Filosofia dell'Universit\u00e0 di Pisa per una ricerca nel quadro del PRIN \"Le forme del Commento filosofico dal tardo-antico al tardo medioevo\" diretto dal prof. Gianfranco Fioravanti",
        "periodo": "dal 01-09-2006 al 31-10-2006"
      },
      {
        "content": "Ricercatore ospite presso la Radboud Universiteit di Nijmegen per uno studio sulla storia della dottrina del libero arbitrio fra XII e primo XIII secolo nel quadro del progetto \"A Genealogy of Morals: The Cardinal Virtues in the Middle Ages\" (Netherlands Organisation of Scientific Research, NOW e Radboud University Nijmegen)",
        "periodo": "dal 01-03-2007 al 30-05-2007"
      },
      {
        "content": "Postdoctoral research fellowship presso la Fondazione per le Scienze Religiose Giovanni XXIII (Bologna, Italy) per uno studio relativo alla genesi, alle caratteristiche e alla fortuna del \"De Servorum Dei beatificatione et beatorum canonizatione\" di Benedetto XIV",
        "periodo": "dal 01-11-2008 al 30-09-2009"
      },
      {
        "content": "Postdoctoral research fellowship presso la ERL7229 Moyen-\u00c2ge, Atelier Vincent de Beauvais: Encyclop\u00e9disme et transmission des connaissances, Universit\u00e9 Nancy2, France, per uno studio delle sezioni di Metafisica ed Etica di un anonimo \"Compendium philosophiae\" (met\u00e0 del XIII secolo) e preparazione dell'edizione critica del testo",
        "periodo": "dal 01-10-2009 al 30-09-2010"
      },
      {
        "content": "Postdoctoral research fellowship presso la Fondazione per le Scienze Religiose Giovanni XXIII (Bologna, Italy) per una ricerca sulla Bibbia di Marco Polo (studio codicologico e paleografico e studio della storia del testo biblico nel XIII secolo)",
        "periodo": "dal 01-10-2010 al 14-01-2012"
      },
      {
        "content": "Postdoctoral research fellowship in filosofia medievale presso il Medieval Institute, Unviersity of Notre Dame (S.I.E.P.M. Fellowship at the Medieval Institute) per una ricerca sulla tradizione di commento alle Sentenze di Pietro Lombardo fra il 1150 e il 1250",
        "periodo": "dal 15-01-2012 al 15-05-2012"
      },
      {
        "content": "Postdoctoral research fellowship presso la Fondazione per le Scienze Religiose Giovanni XXIII (Bologna, Italy) per una ricerca sulla storia della nozione di legge di natura nel pensiero filosofico, teologico e giuridico medievale",
        "periodo": "dal 15-05-2012 al 31-05-2016"
      },
      {
        "content": "Postdoctoral research fellowship presso l'Istituto per la Storia dell'Europa Mediterranea (CNR, Cagliari) per una ricerca sulle prassi ecumeniche fra le chiese cristianes: progetto di ricerca focalizzato sullo studio della genesi e fortuna dei \"Dialoghi\" di Anselmo di Havelberg",
        "periodo": "dal 01-06-2016 a oggi"
      }
    ],
    "Direzione o partecipazione alle attivit\u00e0 di un gruppo di ricerca caratterizzato da": [
      {
        "content": "PARTECIPAZIONE AL PROGETTO INTERNAZIONALE DI EDIZIONE CRITICA DELLE \"QUAESTIONES THEOLOGIAE\" DI STEFANO LANGTON COORDINATO DAL PROF. RICCARDO QUINTO E IN SEGUITO DALLA PROF.SSA MAGDALENA BIENIAK",
        "periodo": "dal 01-11-2008 a oggi"
      },
      {
        "content": "PARTECIPAZIONE AL PROGETTO DI STUDIO SUI TRATTATI TEOLOGICI E GIURIDICI DI BENEDETTO XIV COORDINATO DAL PROF. ALBERTO MELLONI, PRESSO LA FONDAZIONE PER LE SCIENZE RELIGIOSE GIOVANNI XXIII (BOLOGNA, ITALY),",
        "periodo": "dal 01-11-2008 al 30-09-2009"
      },
      {
        "content": "PARTECIPAZIONE AL PROGETTO DI RICERCA INTERNAZIONALE SULLA BIBBIA DI MARCO POLO COORDINATO DAL PROF. ALBERTO MELLONI PRESSO LA FONDAZIONE PER LE SCIENZE RELIGIOSE GIOVANNI XXIII (BOLOGNA, ITALY)",
        "periodo": "dal 01-10-2010 al 14-01-2012"
      },
      {
        "content": "PARTECIPAZIONE AL GRUPPO DI RICERCA SULLA STORIA DEL RAPPORTO FRA IDEA DI NATURA E MAGISTERO COORDINATO DAL PROF. ALBERTO MELLONI PRESSO LA FONDAZIONE PER LE SCIENZE RELIGIOSE GIOVANNI XXIII (BOLOGNA, ITALY)",
        "periodo": "dal 15-05-2012 al 31-05-2016"
      },
      {
        "content": "DIREZIONE DELLA SEZIONE 1150-1250 DEL PROGETTO DI RICERCA INTERNAZIONALE \"COMMENTARIES ON THE SENTENCES OF PETER LOMBARD\" DELLA S.I.E.P.M. (SOCIETE INTERNATIONALE POUR L'ETUDE DE LA PHILOSOPHIE MEDIEVALE)",
        "periodo": "dal 01-08-2014 a oggi"
      }
    ],
    "Formale attribuzione di incarichi di insegnamento o di ricerca (fellowship) presso": [
      {
        "content": "SEMINARIO \"THE LATIN TREATISES OF PROSPERO LABERTINI, POPE BENEDICT XIV\", NEL QUADRO DELLA SUMMER SCHOOL INTERNAZIONALE DI REFO500 \"READING LATIN SOURCES BETWEEN LUTHER AND VATICAN II\" (BOLOGNA",
        "periodo": "dal 26-08-2013 al 30-08-2013"
      },
      {
        "content": "SEMINARIO SU \"BIBBIA, MANOSCRITTI E CULTURA NELL'EUROPA MEDIEVALE\" - PROGETTO \"FORMAZIONE IN SMART CULTURE E TURISMO\", UNIVERSITA\u00ec DI LECCE, CORSO DI METODOLOGIA DELLA RICERCA SCIENTIFICA IN DISCIPLINE UMANISTICHE\"",
        "periodo": "dal 09-07-2014 al 10-07-2014"
      },
      {
        "content": "CULTORE DELLA MATERIA - CORSO SULLE RELIGIONI MONOTEISTICHE E STUDI RELIGIOSI NEL QUADRO DEL CORSO DI STORIA DELLE RELAZIONI INTERRELIGIOSE (PROF. ALBERTO MELLONI), UNIVERSITA' DI MODENA E REGGIO EMILIA",
        "periodo": "dal 01-09-2014 al 31-08-2015"
      },
      {
        "content": "SEMINARIO SU \"LA RISERVA PAPALE IN MATERIA DI CANONIZZAZIONE\" - ALTA SCUOLA DI SCIENZE RELIGIOSE \"G. ALBERIGO\", FONDAZIONE PER LE SCIENZE RELIGIOSE \"GIOVANNI XXIII\" (BOLOGNA, ITALY)",
        "periodo": "dal 10-09-2014 al 10-09-2014"
      },
      {
        "content": "ORGANIZZAZIONE DELLA SUMMER SCHOOL INTERNAZIONALE \"LAW, RIGHTS, AND RELIGION FACING THE REFORM\" DEL NETWORK INTERNAZIOANLE REFO500, BOLOGNA",
        "periodo": "dal 24-08-2015 al 28-08-2015"
      },
      {
        "content": "SEMINARIO \"NATURAL LAW AND THE PASSAGE FROM MEDIEVAL TO MODERN AGE: A DEBATED POINT\" NELL'AMBITO DELLA SUMMER SCHOOL INTERNAZIONALE DI REFO500 \"LAW, RIGTHS, AND RELIGION FACING THE REFORM\", BOLOGNA",
        "periodo": "dal 24-08-2015 al 28-08-2015"
      },
      {
        "content": "CULTORE DELLA MATERIA - CORSO SULLE RELIGIONI MONOTEISTICHE E STUDI RELIGIOSI NEL QUADRO DEL CORSO DI STORIA DELLE RELAZIONI INTERRELIGIOSE (PROF. ALBERTO MELLONI), UNIVERSITA' DI MODENA E REGGIO EMILIA",
        "periodo": "dal 01-09-2015 al 31-08-2016"
      },
      {
        "content": "PROFESSORE A CONTRATTO DI STORIA DELLA FILOSOFIA MEDIEVALE (LM) PRESSO L'UNIVERSITA' DI BOLOGNA",
        "periodo": "dal 01-09-2015 al 31-08-2016"
      },
      {
        "content": "CULTORE DELLA MATERIA - CORSO SULLE RELIGIONI MONOTEISTICHE E STUDI RELIGIOSI NEL QUADRO DEL CORSO DI STORIA DELLE RELAZIONI INTERRELIGIOSE (PROF. ALBERTO MELLONI), UNIVERSITA' DI MODENA E REGGIO EMILIA",
        "periodo": "dal 01-09-2016 a oggi"
      }
    ]
  }
}